tests/__init__.py
tests/test_addr_view.py
tests/test_api_schema.py
tests/test_database.py
tests/test_file_logger.py
tests/test_firewall.py
tests/test_healthcheck.py
tests/test_log_sender.py
tests/test_portmap_view.py
tests/test_shell.py
tests/test_worker.py
vlab_ipam_api/__init__.py
vlab_ipam_api/app.ini
vlab_ipam_api/app.py
vlab_ipam_api/ddns_updater.py
vlab_ipam_api/log_sender.py
vlab_ipam_api/vlab-ddns-updater.service
vlab_ipam_api/vlab-ipam.service
vlab_ipam_api/vlab-log-sender.service
vlab_ipam_api/vlab-worker.service
vlab_ipam_api/worker.py
vlab_ipam_api/lib/__init__.py
vlab_ipam_api/lib/constants.py
vlab_ipam_api/lib/database.py
vlab_ipam_api/lib/exceptions.py
vlab_ipam_api/lib/file_logger.py
vlab_ipam_api/lib/firewall.py
vlab_ipam_api/lib/shell.py
vlab_ipam_api/lib/views/__init__.py
vlab_ipam_api/lib/views/addr.py
vlab_ipam_api/lib/views/healthcheck.py
vlab_ipam_api/lib/views/portmap.py
vlab_ipam_api-2019.7.3.dist-info/METADATA
vlab_ipam_api-2019.7.3.dist-info/WHEEL
vlab_ipam_api-2019.7.3.dist-info/top_level.txt
vlab_ipam_api-2019.7.3.dist-info/RECORD
