Metadata-Version: 2.1
Name: vlab-ipam-api
Version: 2019.7.3
Summary: A RESTful API for automated IPAM of a personal lab in vLab
Home-page: UNKNOWN
Author: Nicholas Willhite,
Author-email: willnx84@gmail.com
License: UNKNOWN
Platform: UNKNOWN
Classifier: Development Status :: 4 - Beta
Classifier: Intended Audience :: Developers
Classifier: License :: OSI Approved :: Apache Software License
Classifier: Natural Language :: English
Classifier: Operating System :: POSIX :: Linux
Classifier: Programming Language :: Python :: 3.6
Requires-Dist: flask
Requires-Dist: pyjwt
Requires-Dist: uwsgi
Requires-Dist: vlab-api-common
Requires-Dist: psycopg2
Requires-Dist: ujson
Requires-Dist: cryptography
Requires-Dist: setproctitle
Requires-Dist: kafka-python
Requires-Dist: dnspython
